poetry_update_editable/__init__.py
poetry_update_editable/command.py
poetry_update_editable/plugin.py
poetry_update_editable/py.typed
poetry_update_editable_plugin-0.0.5.dist-info/LICENSE
poetry_update_editable_plugin-0.0.5.dist-info/METADATA
poetry_update_editable_plugin-0.0.5.dist-info/WHEEL
poetry_update_editable_plugin-0.0.5.dist-info/entry_points.txt
poetry_update_editable_plugin-0.0.5.dist-info/RECORD
