Metadata-Version: 2.1
Name: poetry-update-editable-plugin
Version: 0.0.5
Summary: A poetry plugin to automatically update all editable dependencies.
License: MIT
Author: Chris Brousseau
Author-email: chris@cbrews.xyz
Requires-Python: >=3.9,<4.0
Classifier: License :: OSI Approved :: MIT License
Classifier: Programming Language :: Python :: 3
Classifier: Programming Language :: Python :: 3.9
Classifier: Programming Language :: Python :: 3.10
Classifier: Programming Language :: Python :: 3.11
Requires-Dist: httpx (>=0.25.0,<0.26.0)
Requires-Dist: poetry (>=1.4,<2.0)
